{"v":"5.5.7","meta":{"g":"LottieFiles AE 0.1.20","a":"","k":"","d":"","tc":""},"fr":25,"ip":0,"op":41,"w":800,"h":800,"nm":"shopping","ddd":0,"assets":[],"layers":[{"ddd":0,"ind":1,"ty":3,"nm":"car controller","sr":1,"ks":{"o":{"a":0,"k":0,"ix":11},"r":{"a":0,"k":0,"ix":10},"p":{"s":true,"x":{"a":1,"k":[{"i":{"x":[0.833],"y":[0.833]},"o":{"x":[0.167],"y":[0.167]},"t":0,"s":[944]},{"t":15,"s":[392]}],"ix":3},"y":{"a":0,"k":554,"ix":4}},"a":{"a":0,"k":[0,0,0],"ix":1},"s":{"a":0,"k":[100,100,100],"ix":6}},"ao":0,"ef":[{"ty":5,"nm":"Wiggle - position","np":4,"mn":"ADBE CM WigglePosition","ix":1,"en":1,"ef":[{"ty":0,"nm":"Wiggle Speed (wigs/sec)","mn":"ADBE CM WigglePosition-0001","ix":1,"v":{"a":0,"k":1,"ix":1}},{"ty":0,"nm":"Wiggle Amount (pixels)","mn":"ADBE CM WigglePosition-0002","ix":2,"v":{"a":0,"k":50,"ix":2}}]},{"ty":5,"nm":"(Transform)","np":14,"mn":"ADBE Geometry2","ix":2,"en":1,"ef":[{"ty":3,"nm":"Anchor Point","mn":"ADBE Geometry2-0001","ix":1,"v":{"a":0,"k":[0,0],"ix":1}},{"ty":3,"nm":"Position","mn":"ADBE Geometry2-0002","ix":2,"v":{"a":0,"k":[0,0],"ix":2,"x":"var $bm_rt;\n$bm_rt = wiggle(effect('Wiggle - position')('Wiggle Speed (wigs/sec)'), effect('Wiggle - position')('Wiggle Amount (pixels)'));"}},{"ty":7,"nm":"Uniform Scale","mn":"ADBE Geometry2-0011","ix":3,"v":{"a":0,"k":1,"ix":3}},{"ty":0,"nm":"Scale","mn":"ADBE Geometry2-0003","ix":4,"v":{"a":0,"k":100,"ix":4}},{"ty":0,"nm":" ","mn":"ADBE Geometry2-0004","ix":5,"v":{"a":0,"k":100,"ix":5}},{"ty":0,"nm":"Skew","mn":"ADBE Geometry2-0005","ix":6,"v":{"a":0,"k":0,"ix":6}},{"ty":0,"nm":"Skew Axis","mn":"ADBE Geometry2-0006","ix":7,"v":{"a":0,"k":0,"ix":7}},{"ty":0,"nm":"Rotation","mn":"ADBE Geometry2-0007","ix":8,"v":{"a":0,"k":0,"ix":8}},{"ty":0,"nm":"Opacity","mn":"ADBE Geometry2-0008","ix":9,"v":{"a":0,"k":100,"ix":9}},{"ty":7,"nm":"Use Composition’s Shutter Angle","mn":"ADBE Geometry2-0009","ix":10,"v":{"a":0,"k":1,"ix":10}},{"ty":0,"nm":"Shutter Angle","mn":"ADBE Geometry2-0010","ix":11,"v":{"a":0,"k":0,"ix":11}},{"ty":7,"nm":"Sampling","mn":"ADBE Geometry2-0012","ix":12,"v":{"a":0,"k":1,"ix":12}}]}],"ip":0,"op":132,"st":0,"bm":0,"completed":true},{"ddd":0,"ind":2,"ty":4,"nm":"Shape Layer 3","sr":1,"ks":{"o":{"a":0,"k":100,"ix":11},"r":{"a":0,"k":-16,"ix":10},"p":{"a":0,"k":[406,386,0],"ix":2},"a":{"a":0,"k":[0,0,0],"ix":1},"s":{"a":0,"k":[95.455,90,100],"ix":6}},"ao":0,"shapes":[{"ty":"gr","it":[{"ind":0,"ty":"sh","ix":1,"ks":{"a":0,"k":{"i":[[-80,-90],[-112,-122]],"o":[[-80,-90],[-152,-134]],"v":[[-80,-90],[-132,-128]],"c":false},"ix":2},"nm":"Path 1","mn":"ADBE Vector Shape - Group","hd":false,"_render":true},{"ty":"tm","s":{"a":1,"k":[{"i":{"x":[0.833],"y":[0.833]},"o":{"x":[0.167],"y":[0.167]},"t":20,"s":[0]},{"t":22,"s":[50]}],"ix":1},"e":{"a":1,"k":[{"i":{"x":[0.833],"y":[0.833]},"o":{"x":[0.167],"y":[0.167]},"t":20,"s":[0]},{"i":{"x":[0.833],"y":[0.833]},"o":{"x":[0.167],"y":[0.167]},"t":28,"s":[0]},{"t":30,"s":[50]}],"ix":2},"o":{"a":1,"k":[{"i":{"x":[0.833],"y":[0.833]},"o":{"x":[0.167],"y":[0.167]},"t":20,"s":[0]},{"t":30,"s":[360]}],"ix":3},"m":1,"ix":2,"nm":"Trim Paths 1","mn":"ADBE Vector Filter - Trim","hd":false,"_render":true},{"ty":"st","c":{"a":0,"k":[0.89,0.89,0.89,1],"ix":3},"o":{"a":0,"k":100,"ix":4},"w":{"a":0,"k":2,"ix":5},"lc":1,"lj":1,"ml":4,"bm":0,"nm":"Stroke 1","mn":"ADBE Vector Graphic - Stroke","hd":false,"_render":true},{"ty":"tr","p":{"a":0,"k":[0,0],"ix":2},"a":{"a":0,"k":[0,0],"ix":1},"s":{"a":0,"k":[100,100],"ix":3},"r":{"a":0,"k":0,"ix":6},"o":{"a":0,"k":100,"ix":7},"sk":{"a":0,"k":0,"ix":4},"sa":{"a":0,"k":0,"ix":5},"nm":"Transform","_render":true}],"nm":"Shape 1","np":4,"cix":2,"bm":0,"ix":1,"mn":"ADBE Vector Group","hd":false,"_render":true}],"ip":0,"op":132,"st":0,"bm":0,"completed":true},{"ddd":0,"ind":3,"ty":4,"nm":"Shape Layer 2","sr":1,"ks":{"o":{"a":0,"k":100,"ix":11},"r":{"a":0,"k":0,"ix":10},"p":{"a":0,"k":[400,400,0],"ix":2},"a":{"a":0,"k":[0,0,0],"ix":1},"s":{"a":0,"k":[95.455,90,100],"ix":6}},"ao":0,"shapes":[{"ty":"gr","it":[{"ind":0,"ty":"sh","ix":1,"ks":{"a":0,"k":{"i":[[-80,-90],[-112,-122]],"o":[[-80,-90],[-152,-134]],"v":[[-80,-90],[-132,-128]],"c":false},"ix":2},"nm":"Path 1","mn":"ADBE Vector Shape - Group","hd":false,"_render":true},{"ty":"tm","s":{"a":1,"k":[{"i":{"x":[0.833],"y":[0.833]},"o":{"x":[0.167],"y":[0.167]},"t":20,"s":[0]},{"t":22,"s":[50]}],"ix":1},"e":{"a":1,"k":[{"i":{"x":[0.833],"y":[0.833]},"o":{"x":[0.167],"y":[0.167]},"t":20,"s":[0]},{"i":{"x":[0.833],"y":[0.833]},"o":{"x":[0.167],"y":[0.167]},"t":28,"s":[0]},{"t":30,"s":[50]}],"ix":2},"o":{"a":1,"k":[{"i":{"x":[0.833],"y":[0.833]},"o":{"x":[0.167],"y":[0.167]},"t":20,"s":[0]},{"t":30,"s":[360]}],"ix":3},"m":1,"ix":2,"nm":"Trim Paths 1","mn":"ADBE Vector Filter - Trim","hd":false,"_render":true},{"ty":"st","c":{"a":0,"k":[0.89,0.89,0.89,1],"ix":3},"o":{"a":0,"k":100,"ix":4},"w":{"a":0,"k":2,"ix":5},"lc":1,"lj":1,"ml":4,"bm":0,"nm":"Stroke 1","mn":"ADBE Vector Graphic - Stroke","hd":false,"_render":true},{"ty":"tr","p":{"a":0,"k":[0,0],"ix":2},"a":{"a":0,"k":[0,0],"ix":1},"s":{"a":0,"k":[100,100],"ix":3},"r":{"a":0,"k":0,"ix":6},"o":{"a":0,"k":100,"ix":7},"sk":{"a":0,"k":0,"ix":4},"sa":{"a":0,"k":0,"ix":5},"nm":"Transform","_render":true}],"nm":"Shape 1","np":4,"cix":2,"bm":0,"ix":1,"mn":"ADBE Vector Group","hd":false,"_render":true}],"ip":0,"op":132,"st":0,"bm":0,"completed":true},{"ddd":0,"ind":4,"ty":4,"nm":"Shape Layer 1","sr":1,"ks":{"o":{"a":0,"k":100,"ix":11},"r":{"a":0,"k":0,"ix":10},"p":{"a":0,"k":[400,400,0],"ix":2},"a":{"a":0,"k":[0,0,0],"ix":1},"s":{"a":0,"k":[100,100,100],"ix":6}},"ao":0,"shapes":[{"ty":"gr","it":[{"ty":"rc","d":1,"s":{"a":0,"k":[674.867,19.098],"ix":2},"p":{"a":0,"k":[0,0],"ix":3},"r":{"a":0,"k":0,"ix":4},"nm":"Rectangle Path 1","mn":"ADBE Vector Shape - Rect","hd":false,"_render":true},{"ty":"fl","c":{"a":0,"k":[0.89,0.89,0.89,1],"ix":4},"o":{"a":0,"k":100,"ix":5},"r":1,"bm":0,"nm":"Fill 1","mn":"ADBE Vector Graphic - Fill","hd":false,"_render":true},{"ty":"tr","p":{"a":0,"k":[19.252,222.871],"ix":2},"a":{"a":0,"k":[0,0],"ix":1},"s":{"a":0,"k":[100,15.346],"ix":3},"r":{"a":0,"k":0,"ix":6},"o":{"a":0,"k":100,"ix":7},"sk":{"a":0,"k":0,"ix":4},"sa":{"a":0,"k":0,"ix":5},"nm":"Transform","_render":true}],"nm":"Rectangle 1","np":3,"cix":2,"bm":0,"ix":1,"mn":"ADBE Vector Group","hd":false,"_render":true}],"ip":0,"op":132,"st":0,"bm":0,"completed":true},{"ddd":0,"ind":5,"ty":4,"nm":"box orange","parent":16,"sr":1,"ks":{"o":{"a":0,"k":100,"ix":11},"r":{"a":0,"k":0,"ix":10},"p":{"a":1,"k":[{"i":{"x":0.833,"y":0.833},"o":{"x":0.167,"y":0.167},"t":15,"s":[0,-342,0],"to":[0,57,0],"ti":[-2.833,-57,0]},{"i":{"x":0.833,"y":0.833},"o":{"x":0.167,"y":0.167},"t":19,"s":[0,0,0],"to":[2.833,57,0],"ti":[0,0,0]},{"i":{"x":0.999,"y":1},"o":{"x":0.42,"y":0},"t":24,"s":[17,0,0],"to":null,"ti":null},{"i":{"x":0.833,"y":0.833},"o":{"x":0.167,"y":0.167},"t":31,"s":[0,0,0],"to":null,"ti":null},{"i":{"x":0.999,"y":1},"o":{"x":0.167,"y":0.167},"t":36,"s":[-20,0,0],"to":null,"ti":null},{"t":41,"s":[0,0,0]}],"ix":2},"a":{"a":0,"k":[0,0,0],"ix":1},"s":{"a":0,"k":[100,100,100],"ix":6}},"ao":0,"hasMask":true,"masksProperties":[{"inv":false,"mode":"a","pt":{"a":0,"k":{"i":[[77.816,-164.5],[-61.5,-164.5],[-61.5,-75.809],[77.816,-75.809]],"o":[[77.816,-164.5],[-61.5,-164.5],[-61.5,-75.809],[77.816,-75.809]],"v":[[77.816,-164.5],[-61.5,-164.5],[-61.5,-75.809],[77.816,-75.809]],"c":true},"ix":1},"o":{"a":0,"k":100,"ix":3},"x":{"a":0,"k":0,"ix":4},"nm":"Mask 1"}],"shapes":[{"ty":"gr","it":[{"ty":"gr","it":[{"ty":"gr","it":[{"ind":0,"ty":"sh","ix":1,"ks":{"a":0,"k":{"i":[[93.459,-128.598],[-94.692,-128.598],[-94.692,-129.985],[93.459,-129.985]],"o":[[93.459,-128.598],[-94.692,-128.598],[-94.692,-129.985],[93.459,-129.985]],"v":[[93.459,-128.598],[-94.692,-128.598],[-94.692,-129.985],[93.459,-129.985]],"c":true},"ix":2},"nm":"Path 1","mn":"ADBE Vector Shape - Group","hd":false,"_render":true},{"ty":"fl","c":{"a":0,"k":[1,1,1,1],"ix":4},"o":{"a":0,"k":100,"ix":5},"r":1,"bm":0,"nm":"Fill 1","mn":"ADBE Vector Graphic - Fill","hd":false,"_render":true},{"ty":"tr","p":{"a":0,"k":[0,0],"ix":2},"a":{"a":0,"k":[0,0],"ix":1},"s":{"a":0,"k":[100,100],"ix":3},"r":{"a":0,"k":0,"ix":6},"o":{"a":0,"k":100,"ix":7},"sk":{"a":0,"k":0,"ix":4},"sa":{"a":0,"k":0,"ix":5},"nm":"Transform","_render":true}],"nm":"Group 1","np":2,"cix":2,"bm":0,"ix":1,"mn":"ADBE Vector Group","hd":false,"_render":true},{"ty":"tr","p":{"a":0,"k":[0,0],"ix":2},"a":{"a":0,"k":[0,0],"ix":1},"s":{"a":0,"k":[100,100],"ix":3},"r":{"a":0,"k":0,"ix":6},"o":{"a":0,"k":100,"ix":7},"sk":{"a":0,"k":0,"ix":4},"sa":{"a":0,"k":0,"ix":5},"nm":"Transform","_render":true}],"nm":"Group 1","np":1,"cix":2,"bm":0,"ix":1,"mn":"ADBE Vector Group","hd":false,"_render":true},{"ty":"gr","it":[{"ty":"gr","it":[{"ind":0,"ty":"sh","ix":1,"ks":{"a":0,"k":{"i":[[33.131,-52.089],[31.744,-52.089],[31.744,-180.605],[33.131,-180.605]],"o":[[33.131,-52.089],[31.744,-52.089],[31.744,-180.605],[33.131,-180.605]],"v":[[33.131,-52.089],[31.744,-52.089],[31.744,-180.605],[33.131,-180.605]],"c":true},"ix":2},"nm":"Path 1","mn":"ADBE Vector Shape - Group","hd":false,"_render":true},{"ty":"fl","c":{"a":0,"k":[1,1,1,1],"ix":4},"o":{"a":0,"k":100,"ix":5},"r":1,"bm":0,"nm":"Fill 1","mn":"ADBE Vector Graphic - Fill","hd":false,"_render":true},{"ty":"tr","p":{"a":0,"k":[0,0],"ix":2},"a":{"a":0,"k":[0,0],"ix":1},"s":{"a":0,"k":[100,100],"ix":3},"r":{"a":0,"k":0,"ix":6},"o":{"a":0,"k":100,"ix":7},"sk":{"a":0,"k":0,"ix":4},"sa":{"a":0,"k":0,"ix":5},"nm":"Transform","_render":true}],"nm":"Group 1","np":2,"cix":2,"bm":0,"ix":1,"mn":"ADBE Vector Group","hd":false,"_render":true},{"ty":"tr","p":{"a":0,"k":[0,0],"ix":2},"a":{"a":0,"k":[0,0],"ix":1},"s":{"a":0,"k":[100,100],"ix":3},"r":{"a":0,"k":0,"ix":6},"o":{"a":0,"k":100,"ix":7},"sk":{"a":0,"k":0,"ix":4},"sa":{"a":0,"k":0,"ix":5},"nm":"Transform","_render":true}],"nm":"Group 2","np":1,"cix":2,"bm":0,"ix":2,"mn":"ADBE Vector Group","hd":false,"_render":true},{"ty":"tr","p":{"a":0,"k":[0,0],"ix":2},"a":{"a":0,"k":[0,0],"ix":1},"s":{"a":0,"k":[100,100],"ix":3},"r":{"a":0,"k":0,"ix":6},"o":{"a":0,"k":100,"ix":7},"sk":{"a":0,"k":0,"ix":4},"sa":{"a":0,"k":0,"ix":5},"nm":"Transform","_render":true}],"nm":"Group 1","np":2,"cix":2,"bm":0,"ix":1,"mn":"ADBE Vector Group","hd":false,"_render":true},{"ty":"gr","it":[{"ind":0,"ty":"sh","ix":1,"ks":{"a":0,"k":{"i":[[71.302,-77.977],[-47.307,-77.977],[-61.176,-84.185],[-61.176,-150.094],[-54.966,-163.962],[63.642,-163.962],[77.51,-157.753],[77.51,-91.845]],"o":[[63.642,-77.977],[-54.966,-77.977],[-61.176,-91.845],[-61.176,-157.753],[-47.307,-163.962],[71.302,-163.962],[77.51,-150.094],[77.51,-84.185]],"v":[[63.642,-77.977],[-47.307,-77.977],[-61.176,-91.845],[-61.176,-150.094],[-47.307,-163.962],[63.642,-163.962],[77.51,-150.094],[77.51,-91.845]],"c":true},"ix":2},"nm":"Path 1","mn":"ADBE Vector Shape - Group","hd":false,"_render":true},{"ty":"fl","c":{"a":0,"k":[0.7176,0.8392,0.2078,1],"ix":4},"o":{"a":0,"k":100,"ix":5},"r":1,"bm":0,"nm":"Fill 1","mn":"ADBE Vector Graphic - Fill","hd":false,"_render":true},{"ty":"tr","p":{"a":0,"k":[0,0],"ix":2},"a":{"a":0,"k":[0,0],"ix":1},"s":{"a":0,"k":[100,100],"ix":3},"r":{"a":0,"k":0,"ix":6},"o":{"a":0,"k":100,"ix":7},"sk":{"a":0,"k":0,"ix":4},"sa":{"a":0,"k":0,"ix":5},"nm":"Transform","_render":true}],"nm":"bg","np":2,"cix":2,"bm":0,"ix":2,"mn":"ADBE Vector Group","hd":false,"_render":true}],"ip":0,"op":132,"st":0,"bm":0,"completed":true},{"ddd":0,"ind":6,"ty":4,"nm":"package1","parent":5,"sr":1,"ks":{"o":{"a":0,"k":100,"ix":11},"r":{"a":0,"k":0,"ix":10},"p":{"a":1,"k":[{"i":{"x":0.833,"y":0.833},"o":{"x":0.167,"y":0.167},"t":20,"s":[-36.987,-191.237,0],"to":null,"ti":null},{"i":{"x":0.999,"y":1},"o":{"x":0.42,"y":0},"t":26,"s":[-14.987,-191.237,0],"to":null,"ti":null},{"t":31,"s":[-36.987,-191.237,0]}],"ix":2},"a":{"a":0,"k":[363.013,207.495,0],"ix":1},"s":{"a":0,"k":[100,100,100],"ix":6}},"ao":0,"hasMask":true,"masksProperties":[{"inv":false,"mode":"a","pt":{"a":0,"k":{"i":[[395.89,236.967],[335.387,236.967],[325.88,232.709],[325.88,187.531],[330.136,178.023],[390.639,178.023],[400.147,182.281],[400.147,227.459]],"o":[[390.639,236.967],[330.136,236.967],[325.88,227.459],[325.88,182.281],[335.387,178.023],[395.89,178.023],[400.147,187.531],[400.147,232.709]],"v":[[390.639,236.967],[335.387,236.967],[325.88,227.459],[325.88,187.531],[335.387,178.023],[390.639,178.023],[400.147,187.531],[400.147,227.459]],"c":true},"ix":1},"o":{"a":0,"k":100,"ix":3},"x":{"a":0,"k":0,"ix":4},"nm":"Mask 1"}],"shapes":[{"ty":"gr","it":[{"ty":"gr","it":[{"ty":"gr","it":[{"ind":0,"ty":"sh","ix":1,"ks":{"a":0,"k":{"i":[[0.693,46.691],[-0.693,46.691],[-0.693,-46.691],[0.693,-46.691]],"o":[[0.693,46.691],[-0.693,46.691],[-0.693,-46.691],[0.693,-46.691]],"v":[[0.693,46.691],[-0.693,46.691],[-0.693,-46.691],[0.693,-46.691]],"c":true},"ix":2},"nm":"Path 1","mn":"ADBE Vector Shape - Group","hd":false,"_render":true},{"ty":"fl","c":{"a":0,"k":[1,1,1,1],"ix":4},"o":{"a":0,"k":100,"ix":5},"r":1,"bm":0,"nm":"Fill 1","mn":"ADBE Vector Graphic - Fill","hd":false,"_render":true},{"ty":"tr","p":{"a":0,"k":[0,0],"ix":2},"a":{"a":0,"k":[0,0],"ix":1},"s":{"a":0,"k":[100,100],"ix":3},"r":{"a":0,"k":0,"ix":6},"o":{"a":0,"k":100,"ix":7},"sk":{"a":0,"k":0,"ix":4},"sa":{"a":0,"k":0,"ix":5},"nm":"Transform","_render":true}],"nm":"Group 1","np":2,"cix":2,"bm":0,"ix":1,"mn":"ADBE Vector Group","hd":false,"_render":true},{"ty":"tr","p":{"a":0,"k":[347.376,208.763],"ix":2},"a":{"a":0,"k":[0,0],"ix":1},"s":{"a":0,"k":[100,100],"ix":3},"r":{"a":0,"k":0,"ix":6},"o":{"a":0,"k":100,"ix":7},"sk":{"a":0,"k":0,"ix":4},"sa":{"a":0,"k":0,"ix":5},"nm":"Transform","_render":true}],"nm":"Group 1","np":1,"cix":2,"bm":0,"ix":1,"mn":"ADBE Vector Group","hd":false,"_render":true},{"ty":"tr","p":{"a":0,"k":[347.376,208.763],"ix":2},"a":{"a":0,"k":[347.376,208.763],"ix":1},"s":{"a":0,"k":[100,100],"ix":3},"r":{"a":0,"k":0,"ix":6},"o":{"a":0,"k":100,"ix":7},"sk":{"a":0,"k":0,"ix":4},"sa":{"a":0,"k":0,"ix":5},"nm":"Transform","_render":true}],"nm":"Group 1","np":1,"cix":2,"bm":0,"ix":1,"mn":"ADBE Vector Group","hd":false,"_render":true},{"ty":"gr","it":[{"ty":"gr","it":[{"ind":0,"ty":"sh","ix":1,"ks":{"a":0,"k":{"i":[[32.877,29.472],[-27.626,29.472],[-37.133,25.214],[-37.133,-19.964],[-32.877,-29.472],[27.626,-29.472],[37.133,-25.214],[37.133,19.964]],"o":[[27.626,29.472],[-32.877,29.472],[-37.133,19.964],[-37.133,-25.214],[-27.626,-29.472],[32.877,-29.472],[37.133,-19.964],[37.133,25.214]],"v":[[27.626,29.472],[-27.626,29.472],[-37.133,19.964],[-37.133,-19.964],[-27.626,-29.472],[27.626,-29.472],[37.133,-19.964],[37.133,19.964]],"c":true},"ix":2},"nm":"Path 1","mn":"ADBE Vector Shape - Group","hd":false,"_render":true},{"ty":"fl","c":{"a":0,"k":[0.8132,0.9954,0.0846,1],"ix":4},"o":{"a":0,"k":100,"ix":5},"r":1,"bm":0,"nm":"Fill 1","mn":"ADBE Vector Graphic - Fill","hd":false,"_render":true},{"ty":"tr","p":{"a":0,"k":[0,0],"ix":2},"a":{"a":0,"k":[0,0],"ix":1},"s":{"a":0,"k":[100,100],"ix":3},"r":{"a":0,"k":0,"ix":6},"o":{"a":0,"k":100,"ix":7},"sk":{"a":0,"k":0,"ix":4},"sa":{"a":0,"k":0,"ix":5},"nm":"Transform","_render":true}],"nm":"Group 1","np":2,"cix":2,"bm":0,"ix":1,"mn":"ADBE Vector Group","hd":false,"_render":true},{"ty":"tr","p":{"a":0,"k":[363.013,207.495],"ix":2},"a":{"a":0,"k":[0,0],"ix":1},"s":{"a":0,"k":[100,100],"ix":3},"r":{"a":0,"k":0,"ix":6},"o":{"a":0,"k":100,"ix":7},"sk":{"a":0,"k":0,"ix":4},"sa":{"a":0,"k":0,"ix":5},"nm":"Transform","_render":true}],"nm":"Group 2","np":1,"cix":2,"bm":0,"ix":2,"mn":"ADBE Vector Group","hd":false,"_render":true}],"ip":0,"op":132,"st":0,"bm":0,"completed":true},{"ddd":0,"ind":9,"ty":4,"nm":"shopping car 2","parent":1,"sr":1,"ks":{"o":{"a":0,"k":100,"ix":11},"r":{"a":0,"k":0,"ix":10},"p":{"a":0,"k":[43.557,-83.699,0],"ix":2},"a":{"a":0,"k":[435.557,470.301,0],"ix":1},"s":{"a":0,"k":[100,100,100],"ix":6}},"ao":0,"shapes":[{"ty":"gr","it":[{"ty":"gr","it":[{"ind":0,"ty":"sh","ix":1,"ks":{"a":0,"k":{"i":[[90.581,4.161],[-88.283,4.161],[-92.443,2.298],[-90.581,-4.161],[88.283,-4.161],[92.443,-2.298]],"o":[[88.283,4.161],[-90.581,4.161],[-92.443,-2.298],[-88.283,-4.161],[90.581,-4.161],[92.443,2.298]],"v":[[88.283,4.161],[-88.283,4.161],[-92.443,0],[-88.283,-4.161],[88.283,-4.161],[92.443,0]],"c":true},"ix":2},"nm":"Path 1","mn":"ADBE Vector Shape - Group","hd":false,"_render":true},{"ty":"fl","c":{"a":0,"k":[0.89,0.89,0.89,1],"ix":4},"o":{"a":0,"k":100,"ix":5},"r":1,"bm":0,"nm":"Fill 1","mn":"ADBE Vector Graphic - Fill","hd":false,"_render":true},{"ty":"tr","p":{"a":0,"k":[0,0],"ix":2},"a":{"a":0,"k":[0,0],"ix":1},"s":{"a":0,"k":[100,100],"ix":3},"r":{"a":0,"k":0,"ix":6},"o":{"a":0,"k":100,"ix":7},"sk":{"a":0,"k":0,"ix":4},"sa":{"a":0,"k":0,"ix":5},"nm":"Transform","_render":true}],"nm":"Group 1","np":2,"cix":2,"bm":0,"ix":1,"mn":"ADBE Vector Group","hd":false,"_render":true},{"ty":"tr","p":{"a":0,"k":[387.172,457.404],"ix":2},"a":{"a":0,"k":[0,0],"ix":1},"s":{"a":0,"k":[100,100],"ix":3},"r":{"a":0,"k":0,"ix":6},"o":{"a":0,"k":100,"ix":7},"sk":{"a":0,"k":0,"ix":4},"sa":{"a":0,"k":0,"ix":5},"nm":"Transform","_render":true}],"nm":"Group 1","np":1,"cix":2,"bm":0,"ix":1,"mn":"ADBE Vector Group","hd":false,"_render":true},{"ty":"gr","it":[{"ty":"gr","it":[{"ind":0,"ty":"sh","ix":1,"ks":{"a":0,"k":{"i":[[102.398,4.161],[-100.1,4.161],[-104.261,2.298],[-102.398,-4.161],[100.1,-4.161],[104.261,-2.298]],"o":[[100.1,4.161],[-102.398,4.161],[-104.261,-2.298],[-100.1,-4.161],[102.398,-4.161],[104.261,2.298]],"v":[[100.1,4.161],[-100.1,4.161],[-104.261,0],[-100.1,-4.161],[100.1,-4.161],[104.261,0]],"c":true},"ix":2},"nm":"Path 1","mn":"ADBE Vector Shape - Group","hd":false,"_render":true},{"ty":"fl","c":{"a":0,"k":[0.89,0.89,0.89,1],"ix":4},"o":{"a":0,"k":100,"ix":5},"r":1,"bm":0,"nm":"Fill 1","mn":"ADBE Vector Graphic - Fill","hd":false,"_render":true},{"ty":"tr","p":{"a":0,"k":[0,0],"ix":2},"a":{"a":0,"k":[0,0],"ix":1},"s":{"a":0,"k":[100,100],"ix":3},"r":{"a":0,"k":0,"ix":6},"o":{"a":0,"k":100,"ix":7},"sk":{"a":0,"k":0,"ix":4},"sa":{"a":0,"k":0,"ix":5},"nm":"Transform","_render":true}],"nm":"Group 1","np":2,"cix":2,"bm":0,"ix":1,"mn":"ADBE Vector Group","hd":false,"_render":true},{"ty":"tr","p":{"a":0,"k":[392.038,412.916],"ix":2},"a":{"a":0,"k":[0,0],"ix":1},"s":{"a":0,"k":[100,100],"ix":3},"r":{"a":0,"k":0,"ix":6},"o":{"a":0,"k":100,"ix":7},"sk":{"a":0,"k":0,"ix":4},"sa":{"a":0,"k":0,"ix":5},"nm":"Transform","_render":true}],"nm":"Group 2","np":1,"cix":2,"bm":0,"ix":2,"mn":"ADBE Vector Group","hd":false,"_render":true},{"ty":"gr","it":[{"ty":"gr","it":[{"ind":0,"ty":"sh","ix":1,"ks":{"a":0,"k":{"i":[[3.1950000000000003,67.42],[-0.9169999999999999,65.691],[-7.283,-63.05],[-5.628,-67.297],[0.9129999999999999,-65.759],[7.283,63.054],[5.628,67.301]],"o":[[0.9210000000000003,67.42],[-1.027,63.466],[-7.397,-65.346],[-1.064,-67.56400000000001],[1.027,-63.462],[7.397,65.349],[3.2640000000000002,67.41900000000001]],"v":[[3.124,67.42],[-1.027,63.466],[-7.283,-63.05],[-3.334,-67.411],[1.027,-63.462],[7.283,63.054],[3.334,67.415]],"c":true},"ix":2},"nm":"Path 1","mn":"ADBE Vector Shape - Group","hd":false,"_render":true},{"ty":"fl","c":{"a":0,"k":[0.89,0.89,0.89,1],"ix":4},"o":{"a":0,"k":100,"ix":5},"r":1,"bm":0,"nm":"Fill 1","mn":"ADBE Vector Graphic - Fill","hd":false,"_render":true},{"ty":"tr","p":{"a":0,"k":[0,0],"ix":2},"a":{"a":0,"k":[0,0],"ix":1},"s":{"a":0,"k":[100,100],"ix":3},"r":{"a":0,"k":0,"ix":6},"o":{"a":0,"k":100,"ix":7},"sk":{"a":0,"k":0,"ix":4},"sa":{"a":0,"k":0,"ix":5},"nm":"Transform","_render":true}],"nm":"Group 1","np":2,"cix":2,"bm":0,"ix":1,"mn":"ADBE Vector Group","hd":false,"_render":true},{"ty":"tr","p":{"a":0,"k":[369.446,435.853],"ix":2},"a":{"a":0,"k":[0,0],"ix":1},"s":{"a":0,"k":[100,100],"ix":3},"r":{"a":0,"k":0,"ix":6},"o":{"a":0,"k":100,"ix":7},"sk":{"a":0,"k":0,"ix":4},"sa":{"a":0,"k":0,"ix":5},"nm":"Transform","_render":true}],"nm":"Group 3","np":1,"cix":2,"bm":0,"ix":3,"mn":"ADBE Vector Group","hd":false,"_render":true},{"ty":"gr","it":[{"ty":"gr","it":[{"ind":0,"ty":"sh","ix":1,"ks":{"a":0,"k":{"i":[[10.29,68.113],[6.293,66.651],[-14.19,-63.306],[-12.997,-67.705],[-6.327,-66.86999999999999],[14.19,63.305],[12.997,67.70400000000001]],"o":[[8.062999999999999,68.113],[5.97,64.6],[-14.546999999999999,-65.576],[-8.457,-68.413],[-5.969,-64.6],[14.548,65.575],[10.507,68.09700000000001]],"v":[[10.075,68.113],[5.97,64.6],[-14.19,-63.306],[-10.727,-68.064],[-5.969,-64.6],[14.19,63.305],[10.727,68.063]],"c":true},"ix":2},"nm":"Path 1","mn":"ADBE Vector Shape - Group","hd":false,"_render":true},{"ty":"fl","c":{"a":0,"k":[0.89,0.89,0.89,1],"ix":4},"o":{"a":0,"k":100,"ix":5},"r":1,"bm":0,"nm":"Fill 1","mn":"ADBE Vector Graphic - Fill","hd":false,"_render":true},{"ty":"tr","p":{"a":0,"k":[0,0],"ix":2},"a":{"a":0,"k":[0,0],"ix":1},"s":{"a":0,"k":[100,100],"ix":3},"r":{"a":0,"k":0,"ix":6},"o":{"a":0,"k":100,"ix":7},"sk":{"a":0,"k":0,"ix":4},"sa":{"a":0,"k":0,"ix":5},"nm":"Transform","_render":true}],"nm":"Group 1","np":2,"cix":2,"bm":0,"ix":1,"mn":"ADBE Vector Group","hd":false,"_render":true},{"ty":"tr","p":{"a":0,"k":[329.128,437.941],"ix":2},"a":{"a":0,"k":[0,0],"ix":1},"s":{"a":0,"k":[100,100],"ix":3},"r":{"a":0,"k":0,"ix":6},"o":{"a":0,"k":100,"ix":7},"sk":{"a":0,"k":0,"ix":4},"sa":{"a":0,"k":0,"ix":5},"nm":"Transform","_render":true}],"nm":"Group 4","np":1,"cix":2,"bm":0,"ix":4,"mn":"ADBE Vector Group","hd":false,"_render":true},{"ty":"gr","it":[{"ty":"gr","it":[{"ind":0,"ty":"sh","ix":1,"ks":{"a":0,"k":{"i":[[-1.996,67.42],[-4.351,67.418],[-8.474,65.279],[0.02,-63.53],[2.152,-67.587],[8.475,-65.276],[-0.02,63.533]],"o":[[-4.26,67.42],[-6.738,67.261],[-8.323,62.986],[0.172,-65.82300000000001],[6.738,-67.257],[8.323,-62.983],[-0.16499999999999998,65.732]],"v":[[-4.168,67.42],[-4.445,67.411],[-8.323,62.986],[0.02,-63.53],[4.445,-67.408],[8.323,-62.983],[-0.02,63.533]],"c":true},"ix":2},"nm":"Path 1","mn":"ADBE Vector Shape - Group","hd":false,"_render":true},{"ty":"fl","c":{"a":0,"k":[0.89,0.89,0.89,1],"ix":4},"o":{"a":0,"k":100,"ix":5},"r":1,"bm":0,"nm":"Fill 1","mn":"ADBE Vector Graphic - Fill","hd":false,"_render":true},{"ty":"tr","p":{"a":0,"k":[0,0],"ix":2},"a":{"a":0,"k":[0,0],"ix":1},"s":{"a":0,"k":[100,100],"ix":3},"r":{"a":0,"k":0,"ix":6},"o":{"a":0,"k":100,"ix":7},"sk":{"a":0,"k":0,"ix":4},"sa":{"a":0,"k":0,"ix":5},"nm":"Transform","_render":true}],"nm":"Group 1","np":2,"cix":2,"bm":0,"ix":1,"mn":"ADBE Vector Group","hd":false,"_render":true},{"ty":"tr","p":{"a":0,"k":[408.721,435.853],"ix":2},"a":{"a":0,"k":[0,0],"ix":1},"s":{"a":0,"k":[100,100],"ix":3},"r":{"a":0,"k":0,"ix":6},"o":{"a":0,"k":100,"ix":7},"sk":{"a":0,"k":0,"ix":4},"sa":{"a":0,"k":0,"ix":5},"nm":"Transform","_render":true}],"nm":"Group 5","np":1,"cix":2,"bm":0,"ix":5,"mn":"ADBE Vector Group","hd":false,"_render":true},{"ty":"gr","it":[{"ty":"gr","it":[{"ind":0,"ty":"sh","ix":1,"ks":{"a":0,"k":{"i":[[-9.133000000000001,68.115],[-11.594000000000001,68.09400000000001],[-15.615,65.503],[7.023,-64.665],[9.580000000000002,-68.445],[15.615,-65.504],[-7.023,64.665]],"o":[[-11.354000000000001,68.115],[-14.099,67.658],[-15.222,63.24],[7.417,-66.93],[14.099,-67.65899999999999],[15.222,-63.241],[-7.375,66.68900000000001]],"v":[[-11.117,68.115],[-11.835,68.052],[-15.222,63.24],[7.023,-64.665],[11.835,-68.053],[15.222,-63.241],[-7.023,64.665]],"c":true},"ix":2},"nm":"Path 1","mn":"ADBE Vector Shape - Group","hd":false,"_render":true},{"ty":"fl","c":{"a":0,"k":[0.89,0.89,0.89,1],"ix":4},"o":{"a":0,"k":100,"ix":5},"r":1,"bm":0,"nm":"Fill 1","mn":"ADBE Vector Graphic - Fill","hd":false,"_render":true},{"ty":"tr","p":{"a":0,"k":[0,0],"ix":2},"a":{"a":0,"k":[0,0],"ix":1},"s":{"a":0,"k":[100,100],"ix":3},"r":{"a":0,"k":0,"ix":6},"o":{"a":0,"k":100,"ix":7},"sk":{"a":0,"k":0,"ix":4},"sa":{"a":0,"k":0,"ix":5},"nm":"Transform","_render":true}],"nm":"Group 1","np":2,"cix":2,"bm":0,"ix":1,"mn":"ADBE Vector Group","hd":false,"_render":true},{"ty":"tr","p":{"a":0,"k":[446.954,437.941],"ix":2},"a":{"a":0,"k":[0,0],"ix":1},"s":{"a":0,"k":[100,100],"ix":3},"r":{"a":0,"k":0,"ix":6},"o":{"a":0,"k":100,"ix":7},"sk":{"a":0,"k":0,"ix":4},"sa":{"a":0,"k":0,"ix":5},"nm":"Transform","_render":true}],"nm":"Group 6","np":1,"cix":2,"bm":0,"ix":6,"mn":"ADBE Vector Group","hd":false,"_render":true},{"ty":"gr","it":[{"ty":"gr","it":[{"ind":0,"ty":"sh","ix":1,"ks":{"a":0,"k":{"i":[[20.756999999999998,6.934],[-16.928,6.934],[-23.862,3.83],[-20.758000000000003,-6.934],[16.927,-6.934],[23.862,-3.83]],"o":[[16.927,6.934],[-20.758000000000003,6.934],[-23.862,-3.83],[-16.928,-6.934],[20.756999999999998,-6.934],[23.862,3.83]],"v":[[16.927,6.934],[-16.928,6.934],[-23.862,0],[-16.928,-6.934],[16.927,-6.934],[23.862,0]],"c":true},"ix":2},"nm":"Path 1","mn":"ADBE Vector Shape - Group","hd":false,"_render":true},{"ty":"fl","c":{"a":0,"k":[0.89,0.89,0.89,1],"ix":4},"o":{"a":0,"k":100,"ix":5},"r":1,"bm":0,"nm":"Fill 1","mn":"ADBE Vector Graphic - Fill","hd":false,"_render":true},{"ty":"tr","p":{"a":0,"k":[0,0],"ix":2},"a":{"a":0,"k":[0,0],"ix":1},"s":{"a":0,"k":[100,100],"ix":3},"r":{"a":0,"k":0,"ix":6},"o":{"a":0,"k":100,"ix":7},"sk":{"a":0,"k":0,"ix":4},"sa":{"a":0,"k":0,"ix":5},"nm":"Transform","_render":true}],"nm":"Group 1","np":2,"cix":2,"bm":0,"ix":1,"mn":"ADBE Vector Group","hd":false,"_render":true},{"ty":"tr","p":{"a":0,"k":[574.284,325.56],"ix":2},"a":{"a":0,"k":[0,0],"ix":1},"s":{"a":0,"k":[100,100],"ix":3},"r":{"a":0,"k":0,"ix":6},"o":{"a":0,"k":100,"ix":7},"sk":{"a":0,"k":0,"ix":4},"sa":{"a":0,"k":0,"ix":5},"nm":"Transform","_render":true}],"nm":"Group 11","np":1,"cix":2,"bm":0,"ix":7,"mn":"ADBE Vector Group","hd":false,"_render":true},{"ty":"gr","it":[{"ty":"gr","it":[{"ind":0,"ty":"sh","ix":1,"ks":{"a":0,"k":{"i":[[-23.997,25.811],[-26.642,25.733],[-30.395999999999997,22.416],[-13.197,-25.811],[25.707,-25.811],[29.867,-23.948999999999998],[28.005000000000003,-17.49],[-7.33,-17.49],[-21.788,23.047]],"o":[[-26.171,25.811],[-29.268,24.796],[-29.624,20.251],[-13.197,-25.811],[28.005000000000003,-25.811],[29.867,-19.353],[25.707,-17.49],[-7.33,-17.49],[-22.395,24.75]],"v":[[-25.706,25.811],[-27.104,25.569],[-29.624,20.251],[-13.197,-25.811],[25.707,-25.811],[29.867,-21.651],[25.707,-17.49],[-7.33,-17.49],[-21.788,23.047]],"c":true},"ix":2},"nm":"Path 1","mn":"ADBE Vector Shape - Group","hd":false,"_render":true},{"ty":"fl","c":{"a":0,"k":[0.89,0.89,0.89,1],"ix":4},"o":{"a":0,"k":100,"ix":5},"r":1,"bm":0,"nm":"Fill 1","mn":"ADBE Vector Graphic - Fill","hd":false,"_render":true},{"ty":"tr","p":{"a":0,"k":[0,0],"ix":2},"a":{"a":0,"k":[0,0],"ix":1},"s":{"a":0,"k":[100,100],"ix":3},"r":{"a":0,"k":0,"ix":6},"o":{"a":0,"k":100,"ix":7},"sk":{"a":0,"k":0,"ix":4},"sa":{"a":0,"k":0,"ix":5},"nm":"Transform","_render":true}],"nm":"Group 1","np":2,"cix":2,"bm":0,"ix":1,"mn":"ADBE Vector Group","hd":false,"_render":true},{"ty":"tr","p":{"a":0,"k":[531.592,347.211],"ix":2},"a":{"a":0,"k":[0,0],"ix":1},"s":{"a":0,"k":[100,100],"ix":3},"r":{"a":0,"k":0,"ix":6},"o":{"a":0,"k":100,"ix":7},"sk":{"a":0,"k":0,"ix":4},"sa":{"a":0,"k":0,"ix":5},"nm":"Transform","_render":true}],"nm":"Group 12","np":1,"cix":2,"bm":0,"ix":8,"mn":"ADBE Vector Group","hd":false,"_render":true},{"ty":"gr","it":[{"ty":"gr","it":[{"ind":0,"ty":"sh","ix":1,"ks":{"a":0,"k":{"i":[[74.187,72.395],[71.59599999999999,72.33699999999999],[67.75099999999999,69.229],[108.053,-64.074],[-109.193,-64.074],[-83.971,67.449],[-85.017,71.886],[-91.711,71.272],[-119.261,-72.395],[119.261,-72.395],[76.382,69.437]],"o":[[72.003,72.395],[68.996,71.55099999999999],[68.416,67.029],[108.053,-64.074],[-109.193,-64.074],[-83.537,69.707],[-89.55199999999999,72.745],[-92.143,69.018],[-119.261,-72.395],[119.261,-72.395],[75.837,71.236]],"v":[[72.401,72.395],[71.195,72.216],[68.416,67.029],[108.053,-64.074],[-109.193,-64.074],[-83.971,67.449],[-87.273,72.319],[-92.143,69.018],[-119.261,-72.395],[119.261,-72.395],[76.382,69.437]],"c":true},"ix":2},"nm":"Path 1","mn":"ADBE Vector Shape - Group","hd":false,"_render":true},{"ty":"fl","c":{"a":0,"k":[0.89,0.89,0.89,1],"ix":4},"o":{"a":0,"k":100,"ix":5},"r":1,"bm":0,"nm":"Fill 1","mn":"ADBE Vector Graphic - Fill","hd":false,"_render":true},{"ty":"tr","p":{"a":0,"k":[0,0],"ix":2},"a":{"a":0,"k":[0,0],"ix":1},"s":{"a":0,"k":[100,100],"ix":3},"r":{"a":0,"k":0,"ix":6},"o":{"a":0,"k":100,"ix":7},"sk":{"a":0,"k":0,"ix":4},"sa":{"a":0,"k":0,"ix":5},"nm":"Transform","_render":true}],"nm":"Group 1","np":2,"cix":2,"bm":0,"ix":1,"mn":"ADBE Vector Group","hd":false,"_render":true},{"ty":"tr","p":{"a":0,"k":[392.229,437.095],"ix":2},"a":{"a":0,"k":[0,0],"ix":1},"s":{"a":0,"k":[100,100],"ix":3},"r":{"a":0,"k":0,"ix":6},"o":{"a":0,"k":100,"ix":7},"sk":{"a":0,"k":0,"ix":4},"sa":{"a":0,"k":0,"ix":5},"nm":"Transform","_render":true}],"nm":"Group 13","np":1,"cix":2,"bm":0,"ix":9,"mn":"ADBE Vector Group","hd":false,"_render":true},{"ty":"gr","it":[{"ty":"gr","it":[{"ind":0,"ty":"sh","ix":1,"ks":{"a":0,"k":{"i":[[75.79599999999999,29.35],[-83.309,29.35],[-88.856,26.867],[-86.372,18.255],[59.744,18.255],[77.761,10.171999999999999],[77.761,-0.239],[69.678,-18.255],[-83.309,-18.255],[-88.856,-20.739],[-86.372,-29.35],[59.744,-29.35],[88.856,-16.291],[88.856,0.238]],"o":[[59.744,29.35],[-86.372,29.35],[-88.856,20.740000000000002],[-83.309,18.255],[69.678,18.255],[77.761,0.238],[77.761,-10.173],[59.744,-18.255],[-86.372,-18.255],[-88.856,-26.866],[-83.309,-29.35],[75.79599999999999,-29.35],[88.856,-0.239],[88.856,16.29]],"v":[[59.744,29.35],[-83.309,29.35],[-88.856,23.803],[-83.309,18.255],[59.744,18.255],[77.761,0.238],[77.761,-0.239],[59.744,-18.255],[-83.309,-18.255],[-88.856,-23.803],[-83.309,-29.35],[59.744,-29.35],[88.856,-0.239],[88.856,0.238]],"c":true},"ix":2},"nm":"Path 1","mn":"ADBE Vector Shape - Group","hd":false,"_render":true},{"ty":"fl","c":{"a":0,"k":[0.89,0.89,0.89,1],"ix":4},"o":{"a":0,"k":100,"ix":5},"r":1,"bm":0,"nm":"Fill 1","mn":"ADBE Vector Graphic - Fill","hd":false,"_render":true},{"ty":"tr","p":{"a":0,"k":[0,0],"ix":2},"a":{"a":0,"k":[0,0],"ix":1},"s":{"a":0,"k":[100,100],"ix":3},"r":{"a":0,"k":0,"ix":6},"o":{"a":0,"k":100,"ix":7},"sk":{"a":0,"k":0,"ix":4},"sa":{"a":0,"k":0,"ix":5},"nm":"Transform","_render":true}],"nm":"Group 1","np":2,"cix":2,"bm":0,"ix":1,"mn":"ADBE Vector Group","hd":false,"_render":true},{"ty":"tr","p":{"a":0,"k":[390.311,527.192],"ix":2},"a":{"a":0,"k":[0,0],"ix":1},"s":{"a":0,"k":[100,100],"ix":3},"r":{"a":0,"k":0,"ix":6},"o":{"a":0,"k":100,"ix":7},"sk":{"a":0,"k":0,"ix":4},"sa":{"a":0,"k":0,"ix":5},"nm":"Transform","_render":true}],"nm":"Group 14","np":1,"cix":2,"bm":0,"ix":10,"mn":"ADBE Vector Group","hd":false,"_render":true}],"ip":0,"op":132,"st":0,"bm":0,"completed":true},{"ddd":0,"ind":10,"ty":4,"nm":"rolling R","parent":1,"sr":1,"ks":{"o":{"a":0,"k":100,"ix":11},"r":{"a":1,"k":[{"i":{"x":[0.833],"y":[0.833]},"o":{"x":[0.167],"y":[0.167]},"t":0,"s":[0]},{"i":{"x":[0.833],"y":[0.833]},"o":{"x":[0.167],"y":[0.167]},"t":15,"s":[180]},{"i":{"x":[0.833],"y":[0.833]},"o":{"x":[0.167],"y":[0.167]},"t":16,"s":[180]},{"i":{"x":[0.833],"y":[0.833]},"o":{"x":[0.167],"y":[0.167]},"t":20,"s":[90]},{"i":{"x":[0.833],"y":[0.833]},"o":{"x":[0.167],"y":[0.167]},"t":21,"s":[9]},{"i":{"x":[0.833],"y":[0.833]},"o":{"x":[0.167],"y":[0.167]},"t":31,"s":[180]},{"i":{"x":[0.833],"y":[0.833]},"o":{"x":[0.167],"y":[0.167]},"t":32,"s":[180]},{"t":41,"s":[0]}],"ix":10},"p":{"a":0,"k":[83.655,39.304,0],"ix":2},"a":{"a":0,"k":[453.905,593.304,0],"ix":1},"s":{"a":0,"k":[100,100,100],"ix":6}},"ao":0,"shapes":[{"ty":"gr","it":[{"ty":"gr","it":[{"ind":0,"ty":"sh","ix":1,"ks":{"a":0,"k":{"i":[[-13.38,-7.389],[-7.389,13.38],[13.38,7.39],[7.389,-13.38]],"o":[[-13.38,7.39],[7.389,13.38],[13.38,-7.389],[-7.389,-13.38]],"v":[[-13.38,0],[0,13.38],[13.38,0],[0,-13.38]],"c":true},"ix":2},"nm":"Path 1","mn":"ADBE Vector Shape - Group","hd":false,"_render":true},{"ty":"fl","c":{"a":0,"k":[0.89,0.89,0.89,1],"ix":4},"o":{"a":0,"k":100,"ix":5},"r":1,"bm":0,"nm":"Fill 1","mn":"ADBE Vector Graphic - Fill","hd":false,"_render":true},{"ty":"tr","p":{"a":0,"k":[0,0],"ix":2},"a":{"a":0,"k":[0,0],"ix":1},"s":{"a":0,"k":[61.233,61.233],"ix":3},"r":{"a":0,"k":0,"ix":6},"o":{"a":0,"k":100,"ix":7},"sk":{"a":0,"k":0,"ix":4},"sa":{"a":0,"k":0,"ix":5},"nm":"Transform","_render":true}],"nm":"Group 2","np":2,"cix":2,"bm":0,"ix":1,"mn":"ADBE Vector Group","hd":false,"_render":true},{"ty":"tr","p":{"a":0,"k":[453.905,593.304],"ix":2},"a":{"a":0,"k":[0,0],"ix":1},"s":{"a":0,"k":[100,100],"ix":3},"r":{"a":0,"k":0,"ix":6},"o":{"a":0,"k":100,"ix":7},"sk":{"a":0,"k":0,"ix":4},"sa":{"a":0,"k":0,"ix":5},"nm":"Transform","_render":true}],"nm":"Group 8","np":1,"cix":2,"bm":0,"ix":1,"mn":"ADBE Vector Group","hd":false,"_render":true},{"ty":"gr","it":[{"ty":"gr","it":[{"ind":0,"ty":"sh","ix":1,"ks":{"a":0,"k":{"i":[[-28.673,-15.836],[-15.836,28.673],[28.673,15.835],[15.835,-28.673]],"o":[[-28.673,15.835],[15.835,28.673],[28.673,-15.836],[-15.836,-28.673]],"v":[[-28.673,0],[0,28.673],[28.673,0],[0,-28.673]],"c":true},"ix":2},"nm":"Path 1","mn":"ADBE Vector Shape - Group","hd":false,"_render":true},{"ty":"fl","c":{"a":0,"k":[0.4,0.4,0.4,1],"ix":4},"o":{"a":0,"k":100,"ix":5},"r":1,"bm":0,"nm":"Fill 1","mn":"ADBE Vector Graphic - Fill","hd":false,"_render":true},{"ty":"tr","p":{"a":0,"k":[0,0],"ix":2},"a":{"a":0,"k":[0,0],"ix":1},"s":{"a":0,"k":[100,100],"ix":3},"r":{"a":0,"k":0,"ix":6},"o":{"a":0,"k":100,"ix":7},"sk":{"a":0,"k":0,"ix":4},"sa":{"a":0,"k":0,"ix":5},"nm":"Transform","_render":true}],"nm":"Group 1","np":2,"cix":2,"bm":0,"ix":1,"mn":"ADBE Vector Group","hd":false,"_render":true},{"ty":"tr","p":{"a":0,"k":[453.905,593.304],"ix":2},"a":{"a":0,"k":[0,0],"ix":1},"s":{"a":0,"k":[100,100],"ix":3},"r":{"a":0,"k":0,"ix":6},"o":{"a":0,"k":100,"ix":7},"sk":{"a":0,"k":0,"ix":4},"sa":{"a":0,"k":0,"ix":5},"nm":"Transform","_render":true}],"nm":"Group 10","np":1,"cix":2,"bm":0,"ix":2,"mn":"ADBE Vector Group","hd":false,"_render":true}],"ip":0,"op":132,"st":0,"bm":0,"completed":true},{"ddd":0,"ind":11,"ty":4,"nm":"rolling L","parent":1,"sr":1,"ks":{"o":{"a":0,"k":100,"ix":11},"r":{"a":1,"k":[{"i":{"x":[0.833],"y":[0.833]},"o":{"x":[0.167],"y":[0.167]},"t":0,"s":[0]},{"i":{"x":[0.833],"y":[0.833]},"o":{"x":[0.167],"y":[0.167]},"t":15,"s":[180]},{"i":{"x":[0.833],"y":[0.833]},"o":{"x":[0.167],"y":[0.167]},"t":16,"s":[180]},{"i":{"x":[0.833],"y":[0.833]},"o":{"x":[0.167],"y":[0.167]},"t":20,"s":[90]},{"i":{"x":[0.833],"y":[0.833]},"o":{"x":[0.167],"y":[0.167]},"t":21,"s":[9]},{"i":{"x":[0.833],"y":[0.833]},"o":{"x":[0.167],"y":[0.167]},"t":31,"s":[180]},{"i":{"x":[0.833],"y":[0.833]},"o":{"x":[0.167],"y":[0.167]},"t":32,"s":[180]},{"t":41,"s":[0]}],"ix":10},"p":{"a":0,"k":[-51.345,39.304,0],"ix":2},"a":{"a":0,"k":[453.905,593.304,0],"ix":1},"s":{"a":0,"k":[100,100,100],"ix":6}},"ao":0,"shapes":[{"ty":"gr","it":[{"ty":"gr","it":[{"ind":0,"ty":"sh","ix":1,"ks":{"a":0,"k":{"i":[[-13.38,-7.389],[-7.389,13.38],[13.38,7.39],[7.389,-13.38]],"o":[[-13.38,7.39],[7.389,13.38],[13.38,-7.389],[-7.389,-13.38]],"v":[[-13.38,0],[0,13.38],[13.38,0],[0,-13.38]],"c":true},"ix":2},"nm":"Path 1","mn":"ADBE Vector Shape - Group","hd":false,"_render":true},{"ty":"fl","c":{"a":0,"k":[0.89,0.89,0.89,1],"ix":4},"o":{"a":0,"k":100,"ix":5},"r":1,"bm":0,"nm":"Fill 1","mn":"ADBE Vector Graphic - Fill","hd":false,"_render":true},{"ty":"tr","p":{"a":0,"k":[0,0],"ix":2},"a":{"a":0,"k":[0,0],"ix":1},"s":{"a":0,"k":[61.233,61.233],"ix":3},"r":{"a":0,"k":0,"ix":6},"o":{"a":0,"k":100,"ix":7},"sk":{"a":0,"k":0,"ix":4},"sa":{"a":0,"k":0,"ix":5},"nm":"Transform","_render":true}],"nm":"Group 2","np":2,"cix":2,"bm":0,"ix":1,"mn":"ADBE Vector Group","hd":false,"_render":true},{"ty":"tr","p":{"a":0,"k":[453.905,593.304],"ix":2},"a":{"a":0,"k":[0,0],"ix":1},"s":{"a":0,"k":[100,100],"ix":3},"r":{"a":0,"k":0,"ix":6},"o":{"a":0,"k":100,"ix":7},"sk":{"a":0,"k":0,"ix":4},"sa":{"a":0,"k":0,"ix":5},"nm":"Transform","_render":true}],"nm":"Group 8","np":1,"cix":2,"bm":0,"ix":1,"mn":"ADBE Vector Group","hd":false,"_render":true},{"ty":"gr","it":[{"ty":"gr","it":[{"ind":0,"ty":"sh","ix":1,"ks":{"a":0,"k":{"i":[[-28.673,-15.836],[-15.836,28.673],[28.673,15.835],[15.835,-28.673]],"o":[[-28.673,15.835],[15.835,28.673],[28.673,-15.836],[-15.836,-28.673]],"v":[[-28.673,0],[0,28.673],[28.673,0],[0,-28.673]],"c":true},"ix":2},"nm":"Path 1","mn":"ADBE Vector Shape - Group","hd":false,"_render":true},{"ty":"fl","c":{"a":0,"k":[0.4,0.4,0.4,1],"ix":4},"o":{"a":0,"k":100,"ix":5},"r":1,"bm":0,"nm":"Fill 1","mn":"ADBE Vector Graphic - Fill","hd":false,"_render":true},{"ty":"tr","p":{"a":0,"k":[0,0],"ix":2},"a":{"a":0,"k":[0,0],"ix":1},"s":{"a":0,"k":[100,100],"ix":3},"r":{"a":0,"k":0,"ix":6},"o":{"a":0,"k":100,"ix":7},"sk":{"a":0,"k":0,"ix":4},"sa":{"a":0,"k":0,"ix":5},"nm":"Transform","_render":true}],"nm":"Group 1","np":2,"cix":2,"bm":0,"ix":1,"mn":"ADBE Vector Group","hd":false,"_render":true},{"ty":"tr","p":{"a":0,"k":[453.905,593.304],"ix":2},"a":{"a":0,"k":[0,0],"ix":1},"s":{"a":0,"k":[100,100],"ix":3},"r":{"a":0,"k":0,"ix":6},"o":{"a":0,"k":100,"ix":7},"sk":{"a":0,"k":0,"ix":4},"sa":{"a":0,"k":0,"ix":5},"nm":"Transform","_render":true}],"nm":"Group 10","np":1,"cix":2,"bm":0,"ix":2,"mn":"ADBE Vector Group","hd":false,"_render":true}],"ip":0,"op":132,"st":0,"bm":0,"completed":true},{"ddd":0,"ind":16,"ty":4,"nm":"box","parent":9,"sr":1,"ks":{"o":{"a":0,"k":100,"ix":11},"r":{"a":1,"k":[{"i":{"x":[0.833],"y":[0.833]},"o":{"x":[0.167],"y":[0.167]},"t":18,"s":[0]},{"i":{"x":[0.833],"y":[0.833]},"o":{"x":[0.167],"y":[0.167]},"t":23,"s":[5]},{"i":{"x":[0.833],"y":[0.833]},"o":{"x":[0.167],"y":[0.167]},"t":27,"s":[0]},{"i":{"x":[0.833],"y":[0.833]},"o":{"x":[0.167],"y":[0.167]},"t":32,"s":[-3]},{"t":38,"s":[0]}],"ix":10},"p":{"a":1,"k":[{"i":{"x":0.833,"y":0.833},"o":{"x":0.167,"y":0.167},"t":30,"s":[385.682,499.386,0],"to":null,"ti":null},{"i":{"x":0.833,"y":0.833},"o":{"x":0.167,"y":0.167},"t":32,"s":[377.682,499.386,0],"to":null,"ti":null},{"t":34,"s":[385.682,499.386,0]}],"ix":2},"a":{"a":0,"k":[-14.318,99.386,0],"ix":1},"s":{"a":0,"k":[100,100,100],"ix":6}},"ao":0,"hasMask":true,"masksProperties":[{"inv":false,"mode":"a","pt":{"a":0,"k":{"i":[[49.76,99.541],[-65.29,99.541],[-78.743,93.33200000000001],[-78.743,-65.495],[-72.72,-79.363],[42.33,-79.363],[55.783,-73.155],[55.783,85.673]],"o":[[42.33,99.541],[-72.72,99.541],[-78.743,85.673],[-78.743,-73.155],[-65.29,-79.363],[49.76,-79.363],[55.783,-65.495],[55.783,93.33200000000001]],"v":[[42.33,99.541],[-65.29,99.541],[-78.743,85.673],[-78.743,-65.495],[-65.29,-79.363],[42.33,-79.363],[55.783,-65.495],[55.783,85.673]],"c":true},"ix":1},"o":{"a":0,"k":100,"ix":3},"x":{"a":0,"k":0,"ix":4},"nm":"Mask 1"}],"shapes":[{"ty":"gr","it":[{"ty":"gr","it":[{"ty":"gr","it":[{"ind":0,"ty":"sh","ix":1,"ks":{"a":0,"k":{"i":[[65.2,-56.018],[-95.334,-56.018],[-95.334,-57.405],[65.2,-57.405]],"o":[[65.2,-56.018],[-95.334,-56.018],[-95.334,-57.405],[65.2,-57.405]],"v":[[65.2,-56.018],[-95.334,-56.018],[-95.334,-57.405],[65.2,-57.405]],"c":true},"ix":2},"nm":"Path 1","mn":"ADBE Vector Shape - Group","hd":false,"_render":true},{"ty":"fl","c":{"a":0,"k":[1,1,1,1],"ix":4},"o":{"a":0,"k":100,"ix":5},"r":1,"bm":0,"nm":"Fill 1","mn":"ADBE Vector Graphic - Fill","hd":false,"_render":true},{"ty":"tr","p":{"a":0,"k":[0,0],"ix":2},"a":{"a":0,"k":[0,0],"ix":1},"s":{"a":0,"k":[100,100],"ix":3},"r":{"a":0,"k":0,"ix":6},"o":{"a":0,"k":100,"ix":7},"sk":{"a":0,"k":0,"ix":4},"sa":{"a":0,"k":0,"ix":5},"nm":"Transform","_render":true}],"nm":"Group 1","np":2,"cix":2,"bm":0,"ix":1,"mn":"ADBE Vector Group","hd":false,"_render":true},{"ty":"tr","p":{"a":0,"k":[0,0],"ix":2},"a":{"a":0,"k":[0,0],"ix":1},"s":{"a":0,"k":[100,100],"ix":3},"r":{"a":0,"k":0,"ix":6},"o":{"a":0,"k":100,"ix":7},"sk":{"a":0,"k":0,"ix":4},"sa":{"a":0,"k":0,"ix":5},"nm":"Transform","_render":true}],"nm":"Group 1","np":1,"cix":2,"bm":0,"ix":1,"mn":"ADBE Vector Group","hd":false,"_render":true},{"ty":"tr","p":{"a":0,"k":[0,0],"ix":2},"a":{"a":0,"k":[0,0],"ix":1},"s":{"a":0,"k":[100,100],"ix":3},"r":{"a":0,"k":0,"ix":6},"o":{"a":0,"k":100,"ix":7},"sk":{"a":0,"k":0,"ix":4},"sa":{"a":0,"k":0,"ix":5},"nm":"Transform","_render":true}],"nm":"Group 1","np":1,"cix":2,"bm":0,"ix":1,"mn":"ADBE Vector Group","hd":false,"_render":true},{"ty":"gr","it":[{"ty":"gr","it":[{"ind":0,"ty":"sh","ix":1,"ks":{"a":0,"k":{"i":[[49.76,99.541],[-65.29,99.541],[-78.743,93.33200000000001],[-78.743,-65.495],[-72.72,-79.363],[42.33,-79.363],[55.783,-73.155],[55.783,85.673]],"o":[[42.33,99.541],[-72.72,99.541],[-78.743,85.673],[-78.743,-73.155],[-65.29,-79.363],[49.76,-79.363],[55.783,-65.495],[55.783,93.33200000000001]],"v":[[42.33,99.541],[-65.29,99.541],[-78.743,85.673],[-78.743,-65.495],[-65.29,-79.363],[42.33,-79.363],[55.783,-65.495],[55.783,85.673]],"c":true},"ix":2},"nm":"Path 1","mn":"ADBE Vector Shape - Group","hd":false,"_render":true},{"ty":"fl","c":{"a":0,"k":[0.8,1,0,1],"ix":4},"o":{"a":0,"k":100,"ix":5},"r":1,"bm":0,"nm":"Fill 1","mn":"ADBE Vector Graphic - Fill","hd":false,"_render":true},{"ty":"tr","p":{"a":0,"k":[0,0],"ix":2},"a":{"a":0,"k":[0,0],"ix":1},"s":{"a":0,"k":[100,100],"ix":3},"r":{"a":0,"k":0,"ix":6},"o":{"a":0,"k":100,"ix":7},"sk":{"a":0,"k":0,"ix":4},"sa":{"a":0,"k":0,"ix":5},"nm":"Transform","_render":true}],"nm":"Group 1","np":2,"cix":2,"bm":0,"ix":1,"mn":"ADBE Vector Group","hd":false,"_render":true},{"ty":"tr","p":{"a":0,"k":[0,0],"ix":2},"a":{"a":0,"k":[0,0],"ix":1},"s":{"a":0,"k":[100,100],"ix":3},"r":{"a":0,"k":0,"ix":6},"o":{"a":0,"k":100,"ix":7},"sk":{"a":0,"k":0,"ix":4},"sa":{"a":0,"k":0,"ix":5},"nm":"Transform","_render":true}],"nm":"Group 2","np":1,"cix":2,"bm":0,"ix":2,"mn":"ADBE Vector Group","hd":false,"_render":true}],"ip":0,"op":132,"st":0,"bm":0,"completed":true}],"markers":[],"__complete":true}